{
   "results" : [
      {
         "address_components" : [
            {
               "long_name" : "103",
               "short_name" : "103",
               "types" : [ "subpremise" ]
            },
            {
               "long_name" : "525",
               "short_name" : "525",
               "types" : [ "street_number" ]
            },
            {
               "long_name" : "Belmont Avenue West",
               "short_name" : "Belmont Ave W",
               "types" : [ "route" ]
            },
            {
               "long_name" : "Victoria Hills",
               "short_name" : "Victoria Hills",
               "types" : [ "neighborhood", "political" ]
            },
            {
               "long_name" : "Kitchener",
               "short_name" : "Kitchener",
               "types" : [ "locality", "political" ]
            },
            {
               "long_name" : "Waterloo Regional Municipality",
               "short_name" : "Waterloo Regional Municipality",
               "types" : [ "administrative_area_level_2", "political" ]
            },
            {
               "long_name" : "Ontario",
               "short_name" : "ON",
               "types" : [ "administrative_area_level_1", "political" ]
            },
            {
               "long_name" : "Canada",
               "short_name" : "CA",
               "types" : [ "country", "political" ]
            },
            {
               "long_name" : "N2M 5E2",
               "short_name" : "N2M 5E2",
               "types" : [ "postal_code" ]
            }
         ],
         "formatted_address" : "103-525 Belmont Ave W, Kitchener, ON N2M 5E2, Canada",
         "geometry" : {
            "bounds" : {
               "northeast" : {
                  "lat" : 43.4480121,
                  "lng" : -80.5146348
               },
               "southwest" : {
                  "lat" : 43.4474569,
                  "lng" : -80.51512529999999
               }
            },
            "location" : {
               "lat" : 43.4477894,
               "lng" : -80.51475820000002
            },
            "location_type" : "ROOFTOP",
            "viewport" : {
               "northeast" : {
                  "lat" : 43.4490834802915,
                  "lng" : -80.51353106970849
               },
               "southwest" : {
                  "lat" : 43.4463855197085,
                  "lng" : -80.5162290302915
               }
            }
         },
         "place_id" : "EjQxMDMtNTI1IEJlbG1vbnQgQXZlIFcsIEtpdGNoZW5lciwgT04gTjJNIDVFMiwgQ2FuYWRhIh8aHQoWChQKEgmXm1Q3RPQriBGxqbEvWhCWaxIDMTAz",
         "types" : [ "subpremise" ]
      }
   ],
   "status" : "OK"
}
